LICENSE
MANIFEST.in
README.md
setup.py
ido/.DS_Store
ido/__init__.py
ido/_compat.py
ido/commands.py
ido/utils.py
ido.egg-info/PKG-INFO
ido.egg-info/SOURCES.txt
ido.egg-info/dependency_links.txt
ido.egg-info/entry_points.txt
ido.egg-info/not-zip-safe
ido.egg-info/requires.txt
ido.egg-info/top_level.txt
ido/packages/ido_init.ido
ido/packages/index.txt
ido/packages/nginx.ido
ido/packages/pcre.ido
ido/packages/redis.ido
ido/packages/test_call.ido
ido/packages/zlib.ido
ido/packages/demo/install.ido
test/test_basic.py