Metadata-Version: 1.1
Name: ido
Version: 0.5
Summary: A command tool used to install packages and execute commands.
Home-page: https://github.com/limodou/ido
Author: limodou
Author-email: limodou@gmail.com
License: BSD
Keywords: command tools
Platform: any
Classifier: Development Status :: 2 - Pre-Alpha
Classifier: Intended Audience :: Developers
Classifier: License :: OSI Approved :: BSD License
Classifier: Programming Language :: Python
Classifier: Operating System :: OS Independent
Classifier: Programming Language :: Python :: 2.6
Classifier: Programming Language :: Python :: 2.7
Classifier: Programming Language :: Python :: 3.3
Classifier: Programming Language :: Python :: 3.4
